test/__init__.py
test/main.py
test/test_binary_mapping.py
wg-pyutils/__init__.py
wg_pyutils/__init__.py
wg_pyutils/binary_mapping.py
wg_pyutils-0.0.1.dist-info/LICENSE
wg_pyutils-0.0.1.dist-info/METADATA
wg_pyutils-0.0.1.dist-info/WHEEL
wg_pyutils-0.0.1.dist-info/top_level.txt
wg_pyutils-0.0.1.dist-info/RECORD
