Metadata-Version: 2.1
Name: wg-pyutils
Version: 0.0.1
Summary: This is a Python package containing lots of small and useful functions for reuse
Home-page: https://github.com/wugifer/wg-pyutils
Author: wg
Author-email: wugifer@pku.org.cn
License: UNKNOWN
Platform: UNKNOWN
Classifier: Programming Language :: Python :: 3
Classifier: License :: OSI Approved :: BSD License
Classifier: Operating System :: OS Independent
Requires-Python: >=3.6
